LICENSE
README.md
setup.py
async_spotify/__init__.py
async_spotify/_error_message.py
async_spotify/spotify_errors.py
async_spotify/token_renew_class.py
async_spotify.egg-info/PKG-INFO
async_spotify.egg-info/SOURCES.txt
async_spotify.egg-info/dependency_links.txt
async_spotify.egg-info/requires.txt
async_spotify.egg-info/top_level.txt
async_spotify/api/__init__.py
async_spotify/api/_api_request_maker.py
async_spotify/api/_response_status.py
async_spotify/api/_status_codes.py
async_spotify/api/spotify_api_client.py
async_spotify/api/_endpoints/__init__.py
async_spotify/api/_endpoints/albums.py
async_spotify/api/_endpoints/artists.py
async_spotify/api/_endpoints/browse.py
async_spotify/api/_endpoints/endpoint.py
async_spotify/api/_endpoints/episodes.py
async_spotify/api/_endpoints/follow.py
async_spotify/api/_endpoints/library.py
async_spotify/api/_endpoints/personalization.py
async_spotify/api/_endpoints/player.py
async_spotify/api/_endpoints/playlists.py
async_spotify/api/_endpoints/search.py
async_spotify/api/_endpoints/shows.py
async_spotify/api/_endpoints/tracks.py
async_spotify/api/_endpoints/urls.py
async_spotify/api/_endpoints/user.py
async_spotify/authentification/__init__.py
async_spotify/authentification/spotify_authorization_token.py
async_spotify/authentification/spotify_cookies.py
async_spotify/authentification/authorization_flows/__init__.py
async_spotify/authentification/authorization_flows/authorization_code_flow.py
async_spotify/authentification/authorization_flows/authorization_flow.py
async_spotify/authentification/authorization_flows/client_credentials_flow.py
test/test_auth.py
test/test_auth_flows.py
test/test_general.py
test/test_token_renew_class.py