Metadata-Version: 2.1
Name: async-spotify
Version: 0.4.4
Summary: An async spotify api client
Home-page: https://github.com/HuiiBuh/AsyncSpotify
Author: HuiiBuh
Author-email: nhaderer1@gmail.com
License: UNKNOWN
Keywords: Spotify,Async,API,Wrapper,AioHttp
Platform: UNKNOWN
Classifier: Intended Audience :: Developers
Classifier: Natural Language :: English
Classifier: Topic :: Software Development
Classifier: Environment :: Web Environment
Classifier: Programming Language :: Python :: 3
Classifier: License :: OSI Approved :: MIT License
Classifier: Operating System :: OS Independent
Requires-Python: >=3.6
License-File: LICENSE
